audit/__init__.py
audit/apps.py
audit/backends.py
audit/models.py
audit/settings.py
audit/utils.py
audit/views.py
audit/middleware/__init__.py
audit/middleware/easyaudit.py
audit/migrations/__init__.py
audit/signals/__init__.py
audit/signals/auth_signals.py
audit/signals/model_signals.py
audit/signals/request_signals.py
django_easy_audit_mongo-0.0.3.dist-info/LICENSE
django_easy_audit_mongo-0.0.3.dist-info/METADATA
django_easy_audit_mongo-0.0.3.dist-info/WHEEL
django_easy_audit_mongo-0.0.3.dist-info/top_level.txt
django_easy_audit_mongo-0.0.3.dist-info/RECORD
