Metadata-Version: 2.1
Name: django-easy-audit-mongo
Version: 0.0.3
Summary: Yet another Django audit log app, hopefully the simplest one.
Home-page: https://github.com/proceduretech/django-easy-audit
Author: Sreeraj Rajan
Author-email: rajan.sreeraj@yahoo.com
License: GPL3
Platform: UNKNOWN
Classifier: Environment :: Plugins
Classifier: Framework :: Django
Classifier: Framework :: Django :: 2.2
Classifier: Framework :: Django :: 3.0
Classifier: Framework :: Django :: 3.1
Classifier: Intended Audience :: Developers
Classifier: License :: OSI Approved :: GNU General Public License v3 (GPLv3)
Classifier: Operating System :: OS Independent
Classifier: Programming Language :: Python :: 3
Classifier: Programming Language :: Python :: 3 :: Only
Classifier: Programming Language :: Python :: 3.5
Classifier: Programming Language :: Python :: 3.6
Classifier: Programming Language :: Python :: 3.7
Classifier: Programming Language :: Python :: 3.8
Classifier: Topic :: Software Development :: Libraries :: Python Modules
Requires-Python: >=3.5
Requires-Dist: beautifulsoup4
Requires-Dist: djongo (==1.3.3)
Requires-Dist: sqlparse (==0.2.4)
